afnumpy
afnumpy/core
afnumpy/lib
afnumpy/linalg
