Metadata-Version: 2.1
Name: afnumpy
Version: 1.2
Summary: A GPU-ready drop-in replacement for numpy
Home-page: https://github.com/FilipeMaia/afnumpy
Author: Filipe Maia
Author-email: filipe.c.maia@gmail.com
License: BSD
Download-URL: https://github.com/FilipeMaia/afnumpy/archive/1.2.tar.gz
Keywords: arrayfire,numpy,GPU
Platform: UNKNOWN
Classifier: Development Status :: 3 - Alpha
Classifier: Intended Audience :: Science/Research
Classifier: Topic :: Scientific/Engineering :: Physics
Classifier: License :: OSI Approved :: BSD License
Classifier: Programming Language :: Python :: 2
Classifier: Programming Language :: Python :: 2.6
Classifier: Programming Language :: Python :: 2.7
